Metadata-Version: 1.0
Name: distributions-raptvin
Version: 1.5
Summary: Gaussian distributions, Binomial Distributions
Home-page: UNKNOWN
Author: Tanvesh Takawale
Author-email: tanveshtakawale26@gmail.com
License: UNKNOWN
Platform: UNKNOWN
